{
  "set-button": {
    "button": {
      "primary": {
        "background": {
          "type": "color",
          "value": "{core.color.primary.base}",
          "filePath": "button/button.tokens.json",
          "isSource": true,
          "original": {
            "type": "color",
            "value": "{core.color.primary.base}"
          },
          "attributes": {
            "category": "button",
            "type": "primary",
            "item": "background"
          },
          "path": {
            "0": "button",
            "1": "primary",
            "2": "background"
          }
        },
        "padding": {
          "horizontal": {
            "type": "spacing",
            "value": "1rem",
            "filePath": "button/button.tokens.json",
            "isSource": true,
            "original": {
              "type": "spacing",
              "value": "1rem"
            },
            "attributes": {
              "category": "button",
              "type": "primary",
              "item": "padding",
              "subitem": "horizontal"
            },
            "path": {
              "0": "button",
              "1": "primary",
              "2": "padding",
              "3": "horizontal"
            }
          },
          "vertical": {
            "type": "spacing",
            "value": "0.75rem",
            "filePath": "button/button.tokens.json",
            "isSource": true,
            "original": {
              "type": "spacing",
              "value": "0.75rem"
            },
            "attributes": {
              "category": "button",
              "type": "primary",
              "item": "padding",
              "subitem": "vertical"
            },
            "path": {
              "0": "button",
              "1": "primary",
              "2": "padding",
              "3": "vertical"
            }
          }
        },
        "border": {
          "radius": {
            "type": "borderRadius",
            "value": "0.25rem",
            "filePath": "button/button.tokens.json",
            "isSource": true,
            "original": {
              "type": "borderRadius",
              "value": "0.25rem"
            },
            "attributes": {
              "category": "button",
              "type": "primary",
              "item": "border",
              "subitem": "radius"
            },
            "path": {
              "0": "button",
              "1": "primary",
              "2": "border",
              "3": "radius"
            }
          }
        },
        "hover": {
          "background": {
            "type": "color",
            "value": "{core.color.primary.dark}",
            "filePath": "button/button.tokens.json",
            "isSource": true,
            "original": {
              "type": "color",
              "value": "{core.color.primary.dark}"
            },
            "attributes": {
              "category": "button",
              "type": "primary",
              "item": "hover",
              "subitem": "background"
            },
            "path": {
              "0": "button",
              "1": "primary",
              "2": "hover",
              "3": "background"
            }
          }
        }
      },
      "outline": {
        "background": {
          "type": "color",
          "value": "transparent",
          "filePath": "button/button.tokens.json",
          "isSource": true,
          "original": {
            "type": "color",
            "value": "transparent"
          },
          "attributes": {
            "category": "button",
            "type": "outline",
            "item": "background"
          },
          "path": {
            "0": "button",
            "1": "outline",
            "2": "background"
          }
        },
        "border": {
          "width": {
            "type": "sizing",
            "value": "0.125rem",
            "filePath": "button/button.tokens.json",
            "isSource": true,
            "original": {
              "type": "sizing",
              "value": "0.125rem"
            },
            "attributes": {
              "category": "button",
              "type": "outline",
              "item": "border",
              "subitem": "width"
            },
            "path": {
              "0": "button",
              "1": "outline",
              "2": "border",
              "3": "width"
            }
          },
          "color": {
            "type": "color",
            "value": "{core.color.dark.base}",
            "filePath": "button/button.tokens.json",
            "isSource": true,
            "original": {
              "type": "color",
              "value": "{core.color.dark.base}"
            },
            "attributes": {
              "category": "button",
              "type": "outline",
              "item": "border",
              "subitem": "color"
            },
            "path": {
              "0": "button",
              "1": "outline",
              "2": "border",
              "3": "color"
            }
          }
        },
        "hover": {
          "background": {
            "type": "color",
            "value": "{core.color.light.mild}",
            "filePath": "button/button.tokens.json",
            "isSource": true,
            "original": {
              "type": "color",
              "value": "{core.color.light.mild}"
            },
            "attributes": {
              "category": "button",
              "type": "outline",
              "item": "hover",
              "subitem": "background"
            },
            "path": {
              "0": "button",
              "1": "outline",
              "2": "hover",
              "3": "background"
            }
          }
        }
      }
    }
  },
  "set-core": {
    "core": {
      "color": {
        "primary": {
          "base": {
            "type": "color",
            "value": "{palette.blue.90}",
            "filePath": "color/base.tokens.json",
            "isSource": true,
            "original": {
              "type": "color",
              "value": "{palette.blue.90}"
            },
            "attributes": {
              "category": "core",
              "type": "color",
              "item": "primary",
              "subitem": "base"
            },
            "path": {
              "0": "core",
              "1": "color",
              "2": "primary",
              "3": "base"
            }
          },
          "light": {
            "type": "color",
            "value": "{palette.blue.80}",
            "filePath": "color/base.tokens.json",
            "isSource": true,
            "original": {
              "type": "color",
              "value": "{palette.blue.80}"
            },
            "attributes": {
              "category": "core",
              "type": "color",
              "item": "primary",
              "subitem": "light"
            },
            "path": {
              "0": "core",
              "1": "color",
              "2": "primary",
              "3": "light"
            }
          },
          "dark": {
            "type": "color",
            "value": "{palette.blue.100}",
            "filePath": "color/base.tokens.json",
            "isSource": true,
            "original": {
              "type": "color",
              "value": "{palette.blue.100}"
            },
            "attributes": {
              "category": "core",
              "type": "color",
              "item": "primary",
              "subitem": "dark"
            },
            "path": {
              "0": "core",
              "1": "color",
              "2": "primary",
              "3": "dark"
            }
          }
        },
        "secondary": {
          "base": {
            "type": "color",
            "value": "#ff5722",
            "filePath": "color/base.tokens.json",
            "isSource": true,
            "original": {
              "type": "color",
              "value": "#ff5722"
            },
            "attributes": {
              "category": "core",
              "type": "color",
              "item": "secondary",
              "subitem": "base"
            },
            "path": {
              "0": "core",
              "1": "color",
              "2": "secondary",
              "3": "base"
            }
          },
          "light": {
            "type": "color",
            "value": "#ff9800",
            "filePath": "color/base.tokens.json",
            "isSource": true,
            "original": {
              "type": "color",
              "value": "#ff9800"
            },
            "attributes": {
              "category": "core",
              "type": "color",
              "item": "secondary",
              "subitem": "light"
            },
            "path": {
              "0": "core",
              "1": "color",
              "2": "secondary",
              "3": "light"
            }
          },
          "dark": {
            "type": "color",
            "value": "#f44336",
            "filePath": "color/base.tokens.json",
            "isSource": true,
            "original": {
              "type": "color",
              "value": "#f44336"
            },
            "attributes": {
              "category": "core",
              "type": "color",
              "item": "secondary",
              "subitem": "dark"
            },
            "path": {
              "0": "core",
              "1": "color",
              "2": "secondary",
              "3": "dark"
            }
          }
        },
        "dark": {
          "base": {
            "type": "color",
            "value": "#263238",
            "filePath": "color/base.tokens.json",
            "isSource": true,
            "original": {
              "type": "color",
              "value": "#263238"
            },
            "attributes": {
              "category": "core",
              "type": "color",
              "item": "dark",
              "subitem": "base"
            },
            "path": {
              "0": "core",
              "1": "color",
              "2": "dark",
              "3": "base"
            }
          },
          "mild": {
            "type": "color",
            "value": "#37474f",
            "filePath": "color/base.tokens.json",
            "isSource": true,
            "original": {
              "type": "color",
              "value": "#37474f"
            },
            "attributes": {
              "category": "core",
              "type": "color",
              "item": "dark",
              "subitem": "mild"
            },
            "path": {
              "0": "core",
              "1": "color",
              "2": "dark",
              "3": "mild"
            }
          }
        },
        "light": {
          "base": {
            "type": "color",
            "value": "#f5f5f5",
            "filePath": "color/base.tokens.json",
            "isSource": true,
            "original": {
              "type": "color",
              "value": "#f5f5f5"
            },
            "attributes": {
              "category": "core",
              "type": "color",
              "item": "light",
              "subitem": "base"
            },
            "path": {
              "0": "core",
              "1": "color",
              "2": "light",
              "3": "base"
            }
          },
          "mild": {
            "type": "color",
            "value": "#e0e0e0",
            "filePath": "color/base.tokens.json",
            "isSource": true,
            "original": {
              "type": "color",
              "value": "#e0e0e0"
            },
            "attributes": {
              "category": "core",
              "type": "color",
              "item": "light",
              "subitem": "mild"
            },
            "path": {
              "0": "core",
              "1": "color",
              "2": "light",
              "3": "mild"
            }
          }
        }
      },
      "size": {
        "font": {
          "small": {
            "value": "0.75",
            "comment": "the small size of the font",
            "filePath": "size/font.tokens.json",
            "isSource": true,
            "original": {
              "value": "0.75",
              "comment": "the small size of the font"
            },
            "attributes": {
              "category": "core",
              "type": "size",
              "item": "font",
              "subitem": "small"
            },
            "path": {
              "0": "core",
              "1": "size",
              "2": "font",
              "3": "small"
            }
          },
          "medium": {
            "value": "1",
            "comment": "the medium size of the font",
            "filePath": "size/font.tokens.json",
            "isSource": true,
            "original": {
              "value": "1",
              "comment": "the medium size of the font"
            },
            "attributes": {
              "category": "core",
              "type": "size",
              "item": "font",
              "subitem": "medium"
            },
            "path": {
              "0": "core",
              "1": "size",
              "2": "font",
              "3": "medium"
            }
          },
          "large": {
            "value": "2",
            "comment": "the large size of the font",
            "filePath": "size/font.tokens.json",
            "isSource": true,
            "original": {
              "value": "2",
              "comment": "the large size of the font"
            },
            "attributes": {
              "category": "core",
              "type": "size",
              "item": "font",
              "subitem": "large"
            },
            "path": {
              "0": "core",
              "1": "size",
              "2": "font",
              "3": "large"
            }
          },
          "base": {
            "value": "{core.size.font.medium}",
            "comment": "the base size of the font",
            "filePath": "size/font.tokens.json",
            "isSource": true,
            "original": {
              "value": "{core.size.font.medium}",
              "comment": "the base size of the font"
            },
            "attributes": {
              "category": "core",
              "type": "size",
              "item": "font",
              "subitem": "base"
            },
            "path": {
              "0": "core",
              "1": "size",
              "2": "font",
              "3": "base"
            }
          }
        }
      }
    },
    "radius": {
      "border": {
        "small": {
          "value": "4",
          "type": "Border Radius",
          "filePath": "cureves/radius.tokens.json",
          "isSource": true,
          "original": {
            "value": "4",
            "type": "Border Radius"
          },
          "attributes": {
            "category": "radius",
            "type": "border",
            "item": "small"
          },
          "path": {
            "0": "radius",
            "1": "border",
            "2": "small"
          }
        },
        "medium": {
          "value": "8",
          "type": "Border Radius",
          "filePath": "cureves/radius.tokens.json",
          "isSource": true,
          "original": {
            "value": "8",
            "type": "Border Radius"
          },
          "attributes": {
            "category": "radius",
            "type": "border",
            "item": "medium"
          },
          "path": {
            "0": "radius",
            "1": "border",
            "2": "medium"
          }
        },
        "big": {
          "value": "16",
          "type": "Border Radius",
          "filePath": "cureves/radius.tokens.json",
          "isSource": true,
          "original": {
            "value": "16",
            "type": "Border Radius"
          },
          "attributes": {
            "category": "radius",
            "type": "border",
            "item": "big"
          },
          "path": {
            "0": "radius",
            "1": "border",
            "2": "big"
          }
        }
      }
    }
  },
  "set-semantic": {
    "semantic": {
      "color": {
        "error": {
          "type": "color",
          "value": "#EA0000",
          "filePath": "color/base.tokens.json",
          "isSource": true,
          "original": {
            "type": "color",
            "value": "#EA0000"
          },
          "attributes": {
            "category": "semantic",
            "type": "color",
            "item": "error"
          },
          "path": {
            "0": "semantic",
            "1": "color",
            "2": "error"
          }
        },
        "success": {
          "type": "color",
          "value": "#009639",
          "filePath": "color/base.tokens.json",
          "isSource": true,
          "original": {
            "type": "color",
            "value": "#009639"
          },
          "attributes": {
            "category": "semantic",
            "type": "color",
            "item": "success"
          },
          "path": {
            "0": "semantic",
            "1": "color",
            "2": "success"
          }
        },
        "warning": {
          "type": "color",
          "value": "#F77600",
          "filePath": "color/base.tokens.json",
          "isSource": true,
          "original": {
            "type": "color",
            "value": "#F77600"
          },
          "attributes": {
            "category": "semantic",
            "type": "color",
            "item": "warning"
          },
          "path": {
            "0": "semantic",
            "1": "color",
            "2": "warning"
          }
        }
      }
    }
  },
  "set-palette": {
    "palette": {
      "grey": {
        "10": {
          "value": "#fafafa",
          "type": "color",
          "filePath": "color/palette.tokens.json",
          "isSource": true,
          "original": {
            "value": "#fafafa",
            "type": "color"
          },
          "attributes": {
            "category": "palette",
            "type": "grey",
            "item": "10"
          },
          "path": {
            "0": "palette",
            "1": "grey",
            "2": "10"
          }
        },
        "20": {
          "value": "#f5f5f5",
          "type": "color",
          "filePath": "color/palette.tokens.json",
          "isSource": true,
          "original": {
            "value": "#f5f5f5",
            "type": "color"
          },
          "attributes": {
            "category": "palette",
            "type": "grey",
            "item": "20"
          },
          "path": {
            "0": "palette",
            "1": "grey",
            "2": "20"
          }
        },
        "30": {
          "value": "#eeeeee",
          "type": "color",
          "filePath": "color/palette.tokens.json",
          "isSource": true,
          "original": {
            "value": "#eeeeee",
            "type": "color"
          },
          "attributes": {
            "category": "palette",
            "type": "grey",
            "item": "30"
          },
          "path": {
            "0": "palette",
            "1": "grey",
            "2": "30"
          }
        },
        "40": {
          "value": "#e0e0e0",
          "type": "color",
          "filePath": "color/palette.tokens.json",
          "isSource": true,
          "original": {
            "value": "#e0e0e0",
            "type": "color"
          },
          "attributes": {
            "category": "palette",
            "type": "grey",
            "item": "40"
          },
          "path": {
            "0": "palette",
            "1": "grey",
            "2": "40"
          }
        },
        "50": {
          "value": "#bdbdbd",
          "type": "color",
          "filePath": "color/palette.tokens.json",
          "isSource": true,
          "original": {
            "value": "#bdbdbd",
            "type": "color"
          },
          "attributes": {
            "category": "palette",
            "type": "grey",
            "item": "50"
          },
          "path": {
            "0": "palette",
            "1": "grey",
            "2": "50"
          }
        },
        "60": {
          "value": "#9e9e9e",
          "type": "color",
          "filePath": "color/palette.tokens.json",
          "isSource": true,
          "original": {
            "value": "#9e9e9e",
            "type": "color"
          },
          "attributes": {
            "category": "palette",
            "type": "grey",
            "item": "60"
          },
          "path": {
            "0": "palette",
            "1": "grey",
            "2": "60"
          }
        },
        "70": {
          "value": "#757575",
          "type": "color",
          "filePath": "color/palette.tokens.json",
          "isSource": true,
          "original": {
            "value": "#757575",
            "type": "color"
          },
          "attributes": {
            "category": "palette",
            "type": "grey",
            "item": "70"
          },
          "path": {
            "0": "palette",
            "1": "grey",
            "2": "70"
          }
        },
        "80": {
          "value": "#616161",
          "type": "color",
          "filePath": "color/palette.tokens.json",
          "isSource": true,
          "original": {
            "value": "#616161",
            "type": "color"
          },
          "attributes": {
            "category": "palette",
            "type": "grey",
            "item": "80"
          },
          "path": {
            "0": "palette",
            "1": "grey",
            "2": "80"
          }
        },
        "90": {
          "value": "#424242",
          "type": "color",
          "filePath": "color/palette.tokens.json",
          "isSource": true,
          "original": {
            "value": "#424242",
            "type": "color"
          },
          "attributes": {
            "category": "palette",
            "type": "grey",
            "item": "90"
          },
          "path": {
            "0": "palette",
            "1": "grey",
            "2": "90"
          }
        },
        "100": {
          "value": "#212121",
          "type": "color",
          "filePath": "color/palette.tokens.json",
          "isSource": true,
          "original": {
            "value": "#212121",
            "type": "color"
          },
          "attributes": {
            "category": "palette",
            "type": "grey",
            "item": "100"
          },
          "path": {
            "0": "palette",
            "1": "grey",
            "2": "100"
          }
        }
      },
      "blue": {
        "10": {
          "value": "#e3f2fd",
          "type": "color",
          "filePath": "color/palette.tokens.json",
          "isSource": true,
          "original": {
            "value": "#e3f2fd",
            "type": "color"
          },
          "attributes": {
            "category": "palette",
            "type": "blue",
            "item": "10"
          },
          "path": {
            "0": "palette",
            "1": "blue",
            "2": "10"
          }
        },
        "20": {
          "value": "#bbdefb",
          "type": "color",
          "filePath": "color/palette.tokens.json",
          "isSource": true,
          "original": {
            "value": "#bbdefb",
            "type": "color"
          },
          "attributes": {
            "category": "palette",
            "type": "blue",
            "item": "20"
          },
          "path": {
            "0": "palette",
            "1": "blue",
            "2": "20"
          }
        },
        "30": {
          "value": "#90caf9",
          "type": "color",
          "filePath": "color/palette.tokens.json",
          "isSource": true,
          "original": {
            "value": "#90caf9",
            "type": "color"
          },
          "attributes": {
            "category": "palette",
            "type": "blue",
            "item": "30"
          },
          "path": {
            "0": "palette",
            "1": "blue",
            "2": "30"
          }
        },
        "40": {
          "value": "#64b5f6",
          "type": "color",
          "filePath": "color/palette.tokens.json",
          "isSource": true,
          "original": {
            "value": "#64b5f6",
            "type": "color"
          },
          "attributes": {
            "category": "palette",
            "type": "blue",
            "item": "40"
          },
          "path": {
            "0": "palette",
            "1": "blue",
            "2": "40"
          }
        },
        "50": {
          "value": "#42a5f5",
          "type": "color",
          "filePath": "color/palette.tokens.json",
          "isSource": true,
          "original": {
            "value": "#42a5f5",
            "type": "color"
          },
          "attributes": {
            "category": "palette",
            "type": "blue",
            "item": "50"
          },
          "path": {
            "0": "palette",
            "1": "blue",
            "2": "50"
          }
        },
        "60": {
          "value": "#2196f3",
          "type": "color",
          "filePath": "color/palette.tokens.json",
          "isSource": true,
          "original": {
            "value": "#2196f3",
            "type": "color"
          },
          "attributes": {
            "category": "palette",
            "type": "blue",
            "item": "60"
          },
          "path": {
            "0": "palette",
            "1": "blue",
            "2": "60"
          }
        },
        "70": {
          "value": "#1e88e5",
          "type": "color",
          "filePath": "color/palette.tokens.json",
          "isSource": true,
          "original": {
            "value": "#1e88e5",
            "type": "color"
          },
          "attributes": {
            "category": "palette",
            "type": "blue",
            "item": "70"
          },
          "path": {
            "0": "palette",
            "1": "blue",
            "2": "70"
          }
        },
        "80": {
          "value": "#1976d2",
          "type": "color",
          "filePath": "color/palette.tokens.json",
          "isSource": true,
          "original": {
            "value": "#1976d2",
            "type": "color"
          },
          "attributes": {
            "category": "palette",
            "type": "blue",
            "item": "80"
          },
          "path": {
            "0": "palette",
            "1": "blue",
            "2": "80"
          }
        },
        "90": {
          "value": "#548933",
          "type": "color",
          "filePath": "color/palette.tokens.json",
          "isSource": true,
          "original": {
            "value": "#548933",
            "type": "color"
          },
          "attributes": {
            "category": "palette",
            "type": "blue",
            "item": "90"
          },
          "path": {
            "0": "palette",
            "1": "blue",
            "2": "90"
          }
        },
        "100": {
          "value": "#0d47a1",
          "type": "color",
          "filePath": "color/palette.tokens.json",
          "isSource": true,
          "original": {
            "value": "#0d47a1",
            "type": "color"
          },
          "attributes": {
            "category": "palette",
            "type": "blue",
            "item": "100"
          },
          "path": {
            "0": "palette",
            "1": "blue",
            "2": "100"
          }
        }
      },
      "green": {
        "10": {
          "value": "#e8f5e9",
          "type": "color",
          "filePath": "color/palette.tokens.json",
          "isSource": true,
          "original": {
            "value": "#e8f5e9",
            "type": "color"
          },
          "attributes": {
            "category": "palette",
            "type": "green",
            "item": "10"
          },
          "path": {
            "0": "palette",
            "1": "green",
            "2": "10"
          }
        },
        "20": {
          "value": "#c8e6c9",
          "type": "color",
          "filePath": "color/palette.tokens.json",
          "isSource": true,
          "original": {
            "value": "#c8e6c9",
            "type": "color"
          },
          "attributes": {
            "category": "palette",
            "type": "green",
            "item": "20"
          },
          "path": {
            "0": "palette",
            "1": "green",
            "2": "20"
          }
        },
        "30": {
          "value": "#a5d6a7",
          "type": "color",
          "filePath": "color/palette.tokens.json",
          "isSource": true,
          "original": {
            "value": "#a5d6a7",
            "type": "color"
          },
          "attributes": {
            "category": "palette",
            "type": "green",
            "item": "30"
          },
          "path": {
            "0": "palette",
            "1": "green",
            "2": "30"
          }
        },
        "40": {
          "value": "#81c784",
          "type": "color",
          "filePath": "color/palette.tokens.json",
          "isSource": true,
          "original": {
            "value": "#81c784",
            "type": "color"
          },
          "attributes": {
            "category": "palette",
            "type": "green",
            "item": "40"
          },
          "path": {
            "0": "palette",
            "1": "green",
            "2": "40"
          }
        },
        "50": {
          "value": "#66bb6a",
          "type": "color",
          "filePath": "color/palette.tokens.json",
          "isSource": true,
          "original": {
            "value": "#66bb6a",
            "type": "color"
          },
          "attributes": {
            "category": "palette",
            "type": "green",
            "item": "50"
          },
          "path": {
            "0": "palette",
            "1": "green",
            "2": "50"
          }
        },
        "60": {
          "value": "#4caf50",
          "type": "color",
          "filePath": "color/palette.tokens.json",
          "isSource": true,
          "original": {
            "value": "#4caf50",
            "type": "color"
          },
          "attributes": {
            "category": "palette",
            "type": "green",
            "item": "60"
          },
          "path": {
            "0": "palette",
            "1": "green",
            "2": "60"
          }
        },
        "70": {
          "value": "#43a047",
          "type": "color",
          "filePath": "color/palette.tokens.json",
          "isSource": true,
          "original": {
            "value": "#43a047",
            "type": "color"
          },
          "attributes": {
            "category": "palette",
            "type": "green",
            "item": "70"
          },
          "path": {
            "0": "palette",
            "1": "green",
            "2": "70"
          }
        },
        "80": {
          "value": "#388e3c",
          "type": "color",
          "filePath": "color/palette.tokens.json",
          "isSource": true,
          "original": {
            "value": "#388e3c",
            "type": "color"
          },
          "attributes": {
            "category": "palette",
            "type": "green",
            "item": "80"
          },
          "path": {
            "0": "palette",
            "1": "green",
            "2": "80"
          }
        },
        "90": {
          "value": "#2e7d32",
          "type": "color",
          "filePath": "color/palette.tokens.json",
          "isSource": true,
          "original": {
            "value": "#2e7d32",
            "type": "color"
          },
          "attributes": {
            "category": "palette",
            "type": "green",
            "item": "90"
          },
          "path": {
            "0": "palette",
            "1": "green",
            "2": "90"
          }
        },
        "100": {
          "value": "#1b5e20",
          "type": "color",
          "filePath": "color/palette.tokens.json",
          "isSource": true,
          "original": {
            "value": "#1b5e20",
            "type": "color"
          },
          "attributes": {
            "category": "palette",
            "type": "green",
            "item": "100"
          },
          "path": {
            "0": "palette",
            "1": "green",
            "2": "100"
          }
        }
      },
      "yellow": {
        "10": {
          "value": "#fffde7",
          "type": "color",
          "filePath": "color/palette.tokens.json",
          "isSource": true,
          "original": {
            "value": "#fffde7",
            "type": "color"
          },
          "attributes": {
            "category": "palette",
            "type": "yellow",
            "item": "10"
          },
          "path": {
            "0": "palette",
            "1": "yellow",
            "2": "10"
          }
        },
        "20": {
          "value": "#fff9c4",
          "type": "color",
          "filePath": "color/palette.tokens.json",
          "isSource": true,
          "original": {
            "value": "#fff9c4",
            "type": "color"
          },
          "attributes": {
            "category": "palette",
            "type": "yellow",
            "item": "20"
          },
          "path": {
            "0": "palette",
            "1": "yellow",
            "2": "20"
          }
        },
        "30": {
          "value": "#fff59d",
          "type": "color",
          "filePath": "color/palette.tokens.json",
          "isSource": true,
          "original": {
            "value": "#fff59d",
            "type": "color"
          },
          "attributes": {
            "category": "palette",
            "type": "yellow",
            "item": "30"
          },
          "path": {
            "0": "palette",
            "1": "yellow",
            "2": "30"
          }
        },
        "40": {
          "value": "#fff176",
          "type": "color",
          "filePath": "color/palette.tokens.json",
          "isSource": true,
          "original": {
            "value": "#fff176",
            "type": "color"
          },
          "attributes": {
            "category": "palette",
            "type": "yellow",
            "item": "40"
          },
          "path": {
            "0": "palette",
            "1": "yellow",
            "2": "40"
          }
        },
        "50": {
          "value": "#ffee58",
          "type": "color",
          "filePath": "color/palette.tokens.json",
          "isSource": true,
          "original": {
            "value": "#ffee58",
            "type": "color"
          },
          "attributes": {
            "category": "palette",
            "type": "yellow",
            "item": "50"
          },
          "path": {
            "0": "palette",
            "1": "yellow",
            "2": "50"
          }
        },
        "60": {
          "value": "#ffeb3b",
          "type": "color",
          "filePath": "color/palette.tokens.json",
          "isSource": true,
          "original": {
            "value": "#ffeb3b",
            "type": "color"
          },
          "attributes": {
            "category": "palette",
            "type": "yellow",
            "item": "60"
          },
          "path": {
            "0": "palette",
            "1": "yellow",
            "2": "60"
          }
        },
        "70": {
          "value": "#fdd835",
          "type": "color",
          "filePath": "color/palette.tokens.json",
          "isSource": true,
          "original": {
            "value": "#fdd835",
            "type": "color"
          },
          "attributes": {
            "category": "palette",
            "type": "yellow",
            "item": "70"
          },
          "path": {
            "0": "palette",
            "1": "yellow",
            "2": "70"
          }
        },
        "80": {
          "value": "#fbc02d",
          "type": "color",
          "filePath": "color/palette.tokens.json",
          "isSource": true,
          "original": {
            "value": "#fbc02d",
            "type": "color"
          },
          "attributes": {
            "category": "palette",
            "type": "yellow",
            "item": "80"
          },
          "path": {
            "0": "palette",
            "1": "yellow",
            "2": "80"
          }
        },
        "90": {
          "value": "#f9a825",
          "type": "color",
          "filePath": "color/palette.tokens.json",
          "isSource": true,
          "original": {
            "value": "#f9a825",
            "type": "color"
          },
          "attributes": {
            "category": "palette",
            "type": "yellow",
            "item": "90"
          },
          "path": {
            "0": "palette",
            "1": "yellow",
            "2": "90"
          }
        },
        "100": {
          "value": "#f57f17",
          "type": "color",
          "filePath": "color/palette.tokens.json",
          "isSource": true,
          "original": {
            "value": "#f57f17",
            "type": "color"
          },
          "attributes": {
            "category": "palette",
            "type": "yellow",
            "item": "100"
          },
          "path": {
            "0": "palette",
            "1": "yellow",
            "2": "100"
          }
        }
      },
      "white": {
        "value": "#ffffff",
        "type": "color",
        "filePath": "color/palette.tokens.json",
        "isSource": true,
        "original": {
          "value": "#ffffff",
          "type": "color"
        },
        "attributes": {
          "category": "palette",
          "type": "white"
        },
        "path": {
          "0": "palette",
          "1": "white"
        }
      }
    }
  }
}